{"_invocation_id": "42c167e6-bf93-4586-9fc8-8079b734d7cd", "linked": {"0": {"name": "source.wintershop.bronze.bronze", "type": "source", "succ": [1]}, "1": {"name": "model.wintershop.stg_logs", "type": "model", "succ": [2]}, "2": {"name": "model.wintershop.silver", "type": "model", "succ": [3, 4, 5, 6, 7, 8, 9]}, "3": {"name": "test.wintershop.not_null_silver_ip.8197d890dc", "type": "test"}, "4": {"name": "test.wintershop.not_null_silver_event_ts.e95b31f78c", "type": "test"}, "5": {"name": "test.wintershop.not_null_silver_http_method.7c8ec234a3", "type": "test"}, "6": {"name": "test.wintershop.accepted_values_silver_http_method__GET__POST__PUT__DELETE__HEAD__OPTIONS.884931ec37", "type": "test"}, "7": {"name": "test.wintershop.not_null_silver_status_code.02f3b02097", "type": "test"}, "8": {"name": "test.wintershop.accepted_values_silver_status_code__200__301__302__400__401__403__404__500__503.787b9dcda7", "type": "test"}, "9": {"name": "test.wintershop.not_null_silver_is_bot.aa42818a7b", "type": "test"}}}